resdk/__init__.py
resdk/constants.py
resdk/exceptions.py
resdk/query.py
resdk/resdk_logger.py
resdk/resolwe.py
resdk/uploader.py
resdk/aws/__init__.py
resdk/aws/session.py
resdk/resources/__init__.py
resdk/resources/annotations.py
resdk/resources/background_task.py
resdk/resources/base.py
resdk/resources/collection.py
resdk/resources/data.py
resdk/resources/descriptor.py
resdk/resources/fields.py
resdk/resources/geneset.py
resdk/resources/metadata.py
resdk/resources/permissions.py
resdk/resources/predictions.py
resdk/resources/process.py
resdk/resources/relation.py
resdk/resources/sample.py
resdk/resources/user.py
resdk/resources/utils.py
resdk/resources/variants.py
resdk/resources/kb/__init__.py
resdk/resources/kb/feature.py
resdk/resources/kb/mapping.py
resdk/shortcuts/__init__.py
resdk/shortcuts/collection.py
resdk/shortcuts/sample.py
resdk/tables/__init__.py
resdk/tables/base.py
resdk/tables/methylation.py
resdk/tables/microarray.py
resdk/tables/ml_ready.py
resdk/tables/qc.py
resdk/tables/qc_mappings.py
resdk/tables/rna.py
resdk/tables/variant.py
resdk/utils/__init__.py
resdk/utils/decorators.py
resdk/utils/table_cache.py
resdk-22.2.0.dist-info/licenses/LICENSE
resdk-22.2.0.dist-info/METADATA
resdk-22.2.0.dist-info/WHEEL
resdk-22.2.0.dist-info/top_level.txt
resdk-22.2.0.dist-info/RECORD
