Metadata-Version: 2.4
Name: resdk
Version: 22.2.0
Summary: Resolwe SDK for Python
Author-email: "Genialis, Inc" <dev-team@genialis.com>
License: 
Project-URL: repository, https://github.com/genialis/resolwe-bio-py/
Project-URL: documentation, https://resdk.readthedocs.io/en/latest/
Keywords: bio,bioinformatics,dataflow,django,pipelines,python,resolwe,sdk
Classifier: Development Status :: 5 - Production/Stable
Classifier: Environment :: Console
Classifier: Intended Audience :: Developers
Classifier: Topic :: Software Development :: Libraries :: Python Modules
Classifier: License :: OSI Approved :: Apache Software License
Classifier: Operating System :: OS Independent
Classifier: Programming Language :: Python
Classifier: Programming Language :: Python :: 3
Classifier: Programming Language :: Python :: 3.9
Classifier: Programming Language :: Python :: 3.10
Classifier: Programming Language :: Python :: 3.11
Classifier: Programming Language :: Python :: 3.12
Classifier: Programming Language :: Python :: 3.13
Requires-Python: <3.14,>=3.9
License-File: LICENSE
Requires-Dist: aiohttp>=3.9.3
Requires-Dist: requests
Requires-Dist: urllib3>=2; python_version >= "3.10"
Requires-Dist: slumber>=0.7.1
Requires-Dist: wrapt
Requires-Dist: pytz
Requires-Dist: tzlocal
Requires-Dist: pandas
Requires-Dist: tqdm
Requires-Dist: openpyxl
Requires-Dist: xlrd
Requires-Dist: boto3[crt]
Requires-Dist: boto3-stubs[s3]
Requires-Dist: packaging
Provides-Extra: docs
Requires-Dist: sphinx; extra == "docs"
Requires-Dist: sphinx_rtd_theme; extra == "docs"
Provides-Extra: package
Requires-Dist: twine; extra == "package"
Requires-Dist: check-manifest; extra == "package"
Requires-Dist: build; extra == "package"
Provides-Extra: test
Requires-Dist: black==24.10.0; extra == "test"
Requires-Dist: flake8; extra == "test"
Requires-Dist: isort; extra == "test"
Requires-Dist: mock; extra == "test"
Requires-Dist: pydocstyle[toml]; extra == "test"
Requires-Dist: pytest-cov; extra == "test"
Requires-Dist: types-tqdm; extra == "test"
Requires-Dist: types-slumber; extra == "test"
Dynamic: license-file
